lightly_insights/__init__.py
lightly_insights/analyze.py
lightly_insights/plots.py
lightly_insights/present.py
lightly_insights/py.typed
lightly_insights/static/cdn.jsdelivr.net_npm_bootstrap@5.3.2_dist_js_bootstrap.bundle.min.js
lightly_insights/static/cdn.jsdelivr.net_npm_bootswatch@5_dist_flatly_bootstrap.min.css
lightly_insights/static/favicon.png
lightly_insights/templates/plots.html
lightly_insights/templates/report.html
lightly_insights-0.1.0.dist-info/LICENSE
lightly_insights-0.1.0.dist-info/WHEEL
lightly_insights-0.1.0.dist-info/METADATA
lightly_insights-0.1.0.dist-info/RECORD
