Metadata-Version: 2.1
Name: lightly-insights
Version: 0.1.0
Summary: Get quick insights about your ML dataset.
License: MIT
Author: Lightly.ai
Requires-Python: >=3.7
Classifier: License :: OSI Approved :: MIT License
Classifier: Programming Language :: Python :: 3
Classifier: Programming Language :: Python :: 3.7
Classifier: Programming Language :: Python :: 3.8
Classifier: Programming Language :: Python :: 3.9
Classifier: Programming Language :: Python :: 3.10
Classifier: Programming Language :: Python :: 3.11
Requires-Dist: jinja2 (>=3.1.2,<4.0.0)
Requires-Dist: labelformat (>=0.1.1,<0.2.0)
Requires-Dist: matplotlib (>=3.5)
Requires-Dist: pillow
Requires-Dist: tqdm
